techbox/__init__.py
techbox/boto3_wrapper.py
techbox/cli.py
techbox/elasticsearch.py
techbox/snippets.py
techbox/tls.py
techbox/cloud/__init__.py
techbox/cloud/aws/__init__.py
techbox/cloud/aws/monitor.py
techbox/cloud/gcp/__init__.py
techbox/cloud/gcp/common.py
techbox-0.0.6.dist-info/AUTHORS.rst
techbox-0.0.6.dist-info/LICENSE
techbox-0.0.6.dist-info/METADATA
techbox-0.0.6.dist-info/WHEEL
techbox-0.0.6.dist-info/entry_points.txt
techbox-0.0.6.dist-info/top_level.txt
techbox-0.0.6.dist-info/RECORD
