Metadata-Version: 2.1
Name: techbox
Version: 0.0.6
Summary: A toolbox packed with dependencies
Home-page: https://github.com/andecy64/techbox
Author: Barak Avrahami
Author-email: barak1345@gmail.com
License: MIT license
Keywords: techbox
Platform: UNKNOWN
Classifier: Development Status :: 2 - Pre-Alpha
Classifier: Intended Audience :: Developers
Classifier: License :: OSI Approved :: MIT License
Classifier: Natural Language :: English
Classifier: Programming Language :: Python :: 3
Classifier: Programming Language :: Python :: 3.5
Classifier: Programming Language :: Python :: 3.6
Classifier: Programming Language :: Python :: 3.7
Classifier: Programming Language :: Python :: 3.8
Requires-Python: >=3.5
Requires-Dist: gitpython
Requires-Dist: fire
Requires-Dist: boto3 (==1.12.17)
